LICENSE
test_cookiecutter_pypackage_project/__init__.py
test_cookiecutter_pypackage_project/py.typed
test_cookiecutter_pypackage_project/test_cookiecutter_pypackage_project.py
test_cookiecutter_pypackage_project-0.1.0.dist-info/LICENSE
test_cookiecutter_pypackage_project-0.1.0.dist-info/WHEEL
test_cookiecutter_pypackage_project-0.1.0.dist-info/METADATA
test_cookiecutter_pypackage_project-0.1.0.dist-info/RECORD
