Metadata-Version: 2.1
Name: test-cookiecutter-pypackage-project
Version: 0.1.0
Summary: A test project for my cookiecutter-pypackage repo
Home-page: https://github.com/mgancita/test_cookiecutter_pypackage_project
License: MIT
Author: Marco Gancitano
Author-email: marco.gancitano@example.com
Requires-Python: >=3.7,<4.0
Classifier: Development Status :: 2 - Pre-Alpha
Classifier: Intended Audience :: Developers
Classifier: License :: OSI Approved :: MIT License
Classifier: Natural Language :: English
Classifier: Programming Language :: Python :: 3
Classifier: Programming Language :: Python :: 3.7
Classifier: Programming Language :: Python :: 3.8
Classifier: Programming Language :: Python :: 3.9
